jjutils/DataExplorer.py
jjutils/DataProcessor.py
jjutils/FileHandler.py
jjutils/KMeansAnalysis.py
jjutils/SQLiteCRUD.py
jjutils/__init__.py
jjutils/config.py
jjutils-0.0.10.dist-info/METADATA
jjutils-0.0.10.dist-info/WHEEL
jjutils-0.0.10.dist-info/top_level.txt
jjutils-0.0.10.dist-info/RECORD
