Metadata-Version: 2.1
Name: jjutils
Version: 0.0.10
Requires-Dist: matplotlib ==3.8.0
Requires-Dist: pandas ==1.5.3
Requires-Dist: seaborn ==0.13.0
Requires-Dist: scikit-learn
